pyTerminalUI/__init__.py
pyTerminalUI-1.4.1.dist-info/LICENSE.md
pyTerminalUI-1.4.1.dist-info/METADATA
pyTerminalUI-1.4.1.dist-info/WHEEL
pyTerminalUI-1.4.1.dist-info/top_level.txt
pyTerminalUI-1.4.1.dist-info/RECORD
