Metadata-Version: 2.1
Name: pyTerminalUI
Version: 1.4.1
Summary: A set of helpers to implement a text user interface (TUI) in a terminal.
Home-page: https://github.com/Paebbels/pyTerminalUI
Author: Patrick Lehmann
Author-email: Paebbels@gmail.com
License: UNKNOWN
Project-URL: Documentation, https://pyTerminalUI.readthedocs.io/en/latest/
Project-URL: Source Code, https://github.com/Paebbels/pyTerminalUI
Project-URL: Issue Tracker, https://github.com/Paebbels/pyTerminalUI/issues
Keywords: Python3 Terminal Shell Text User Interface TUI
Platform: UNKNOWN
Classifier: License :: OSI Approved :: Apache Software License
Classifier: Operating System :: OS Independent
Classifier: Programming Language :: Python :: 3 :: Only
Classifier: Programming Language :: Python :: 3.6
Classifier: Programming Language :: Python :: 3.7
Classifier: Programming Language :: Python :: 3.8
Classifier: Programming Language :: Python :: 3.9
Classifier: Development Status :: 5 - Production/Stable
Classifier: Intended Audience :: Developers
Classifier: Topic :: Utilities
Requires-Python: >=3.6
Requires-Dist: colorama (>=0.4.4)
Requires-Dist: pydecor (>=2.0.1)
Requires-Dist: pyExceptions (>=1.1.1)
Requires-Dist: pyMetaClasses (>=1.3.1)
